pythongardenerpersonalpkg/__init__.py
pythongardenerpersonalpkg/core.py
pythongardenerpersonalpkg_openai_api_key_chatgpt_api_key-0.4.dist-info/METADATA
pythongardenerpersonalpkg_openai_api_key_chatgpt_api_key-0.4.dist-info/WHEEL
pythongardenerpersonalpkg_openai_api_key_chatgpt_api_key-0.4.dist-info/top_level.txt
pythongardenerpersonalpkg_openai_api_key_chatgpt_api_key-0.4.dist-info/RECORD
