Metadata-Version: 2.1
Name: pythongardenerpersonalpkg-openai-api-key-chatgpt-api-key
Version: 0.4
Summary: A simple example package with openai api key
Home-page: https://github.com/yourusername/pythongardenerpersonalpkg
Author: Your Name
Author-email: your.email@example.com
Classifier: Programming Language :: Python :: 3
Classifier: License :: OSI Approved :: MIT License
Classifier: Operating System :: OS Independent
